{
  "title": "Spring Cloud Data Flow introduction",
  "description": "A quick introduction to Spring Cloud Data Flow",
  "difficulty": "beginner",
  "time": "2 minutes",
  "details": {
    "steps": [{
      "title": "Step 1 - Start the server and the shell",
      "text": "step1.md"
    },
    {
      "title": "Step 2 - Register applications",
      "text": "step2.md"
    },
    {
      "title": "Step 3 - Create a stream",
      "text": "step3.md"
    }
    ],
    "intro": {
      "text": "intro.md",
      "courseData": "env-init.sh",
      "credits": "The SCDF team"
    },
    "finish": {
      "text": "finish.md"
    }
  },
  "environment": {
    "showdashboard" : "true",
    "dashboards": [{"name": "Data Flow Dashboard", "port": 9393,
      "link": "/dashboard", "url":"/dashboard", "path" : "/dashboard"},
    "uilayout": "terminal",
    "uimessage1": "\u001b[32mYour Interactive Bash Terminal."
  },
  "backend": {
    "imageid": "java8"
  }
}
